medium_publish/.gitignore
medium_publish/__init__.py
medium_publish/copy_to_clipboard.py
medium_publish/env.py
medium_publish/gist_operations.py
medium_publish/hash_util.py
medium_publish/image_processor.py
medium_publish/main.py
medium_publish/process_file.py
medium_publish/s3_file_operations.py
medium_publish-0.2.0.dist-info/METADATA
medium_publish-0.2.0.dist-info/WHEEL
medium_publish-0.2.0.dist-info/entry_points.txt
medium_publish-0.2.0.dist-info/RECORD
