Metadata-Version: 2.1
Name: medium-publish
Version: 0.2.0
Summary: 
Author: Raphael MANSUY
Author-email: raphael.mansuy@gmail.com
Requires-Python: >=3.12,<4.0
Classifier: Programming Language :: Python :: 3
Classifier: Programming Language :: Python :: 3.12
Classifier: Programming Language :: Python :: 3.13
Requires-Dist: beautifulsoup4 (>=4.12.3,<5.0.0)
Requires-Dist: boto3 (>=1.35.24,<2.0.0)
Requires-Dist: click (>=8.1.7,<9.0.0)
Requires-Dist: load-dotenv (>=0.1.0,<0.2.0)
Requires-Dist: markdown (>=3.7,<4.0)
Requires-Dist: markdown2 (>=2.5.0,<3.0.0)
Requires-Dist: pydantic (>=2.9.2,<3.0.0)
Requires-Dist: pygithub (>=2.4.0,<3.0.0)
Requires-Dist: pyperclip (>=1.9.0,<2.0.0)
Requires-Dist: richxerox (>=1.0.1,<2.0.0)
